torch_buddy/__init__.py
torch_buddy/nn/__init__.py
torch_buddy/nn/base.py
torch_buddy/nn/cv.py
torch_buddy/nn/lr_scheduler.py
torch_buddy/nn/nlp.py
torch_buddy/nn/nn_helper.py
torch_buddy/utils/__init__.py
torch_buddy/utils/helper.py
torch_buddy/utils/image.py
torch_buddy/utils/nn.py
torch_buddy/utils/plot.py
torch_buddy-0.0.5.dist-info/LICENSE
torch_buddy-0.0.5.dist-info/METADATA
torch_buddy-0.0.5.dist-info/WHEEL
torch_buddy-0.0.5.dist-info/top_level.txt
torch_buddy-0.0.5.dist-info/RECORD
