Metadata-Version: 2.1
Name: torch-buddy
Version: 0.0.5
Summary: pytorch toolkit
Home-page: https://github.com/NickYi1990/torch_buddy
Author: 鲲(China)
Author-email: 972775099@qq.com
License: UNKNOWN
Platform: UNKNOWN
Classifier: Programming Language :: Python :: 3
Classifier: License :: OSI Approved :: MIT License
Classifier: Operating System :: OS Independent
Requires-Dist: pandas-summary (>=0.0.5)
